odoo/addons/base_tier_validation_board/README.rst
odoo/addons/base_tier_validation_board/__init__.py
odoo/addons/base_tier_validation_board/__manifest__.py
odoo/addons/base_tier_validation_board/i18n/base_tier_validation_board.pot
odoo/addons/base_tier_validation_board/i18n/it.po
odoo/addons/base_tier_validation_board/models/__init__.py
odoo/addons/base_tier_validation_board/models/tier_review.py
odoo/addons/base_tier_validation_board/readme/CONTRIBUTORS.rst
odoo/addons/base_tier_validation_board/readme/DESCRIPTION.rst
odoo/addons/base_tier_validation_board/readme/USAGE.rst
odoo/addons/base_tier_validation_board/security/groups.xml
odoo/addons/base_tier_validation_board/static/description/icon.png
odoo/addons/base_tier_validation_board/static/description/index.html
odoo/addons/base_tier_validation_board/views/tier_review_view.xml
odoo_addon_base_tier_validation_board-16.0.1.0.0.5.dist-info/METADATA
odoo_addon_base_tier_validation_board-16.0.1.0.0.5.dist-info/WHEEL
odoo_addon_base_tier_validation_board-16.0.1.0.0.5.dist-info/top_level.txt
odoo_addon_base_tier_validation_board-16.0.1.0.0.5.dist-info/RECORD
