Metadata-Version: 2.1
Name: odoo-addon-base-tier-validation-board
Version: 16.0.1.0.0.5
Summary: Add Tier Review Boards
Home-page: https://github.com/OCA/server-ux
Author: FrogeFlow, Odoo Community Association (OCA)
Author-email: support@odoo-community.org
License: AGPL-3
Platform: UNKNOWN
Classifier: Programming Language :: Python
Classifier: Framework :: Odoo
Classifier: Framework :: Odoo :: 16.0
Classifier: License :: OSI Approved :: GNU Affero General Public License v3
Classifier: Development Status :: 4 - Beta
Requires-Python: >=3.10
Requires-Dist: odoo-addon-base-tier-validation <16.1dev,>=16.0dev
Requires-Dist: odoo <16.1dev,>=16.0a
